README.md
setup.py
pysec/__init__.py
pysec/cli.py
pysec/pysec.py
pysec_aws.egg-info/PKG-INFO
pysec_aws.egg-info/SOURCES.txt
pysec_aws.egg-info/dependency_links.txt
pysec_aws.egg-info/entry_points.txt
pysec_aws.egg-info/requires.txt
pysec_aws.egg-info/top_level.txt